django_dsl/__init__.py
django_dsl/exceptions.py
django_dsl/lexer.py
django_dsl/parser.py
django_dsl/run.py
django_domain_specific_language-1.2.6.dist-info/LICENSE
django_domain_specific_language-1.2.6.dist-info/METADATA
django_domain_specific_language-1.2.6.dist-info/WHEEL
django_domain_specific_language-1.2.6.dist-info/top_level.txt
django_domain_specific_language-1.2.6.dist-info/RECORD
