Metadata-Version: 2.1
Name: django-domain-specific-language
Version: 1.2.6
Summary: DSL for Django
Home-page: https://github.com/treussart/django-dsl
Author: Treussart Matthieu
Author-email: matthieu@treussart.com
License: GPLv3
Keywords: django dsl domain-specific-language
Platform: UNKNOWN
Classifier: Development Status :: 5 - Production/Stable
Classifier: Intended Audience :: Developers
Classifier: Framework :: Django :: 3.0
Classifier: Topic :: Software Development :: Interpreters
Classifier: License :: OSI Approved :: GNU General Public License v3 (GPLv3)
Classifier: Programming Language :: Python :: 3 :: Only
License-File: LICENSE
Requires-Dist: Django (>=3)
Requires-Dist: ply (>=3)
